COPYING.txt
MANIFEST.in
setup.py
gmsdk/__init__.py
gmsdk/admin.py
gmsdk/agn.py
gmsdk/api.py
gmsdk/app_settings.py
gmsdk/connection.py
gmsdk/exceptions.py
gmsdk/items.py
gmsdk/log.py
gmsdk/models.py
gmsdk/orders.py
gmsdk/products.py
gmsdk/services.py
gmsdk/settings.py
gmsdk/suppliers.py
gmsdk/tests.py
gmsdk/urls.py
gmsdk/utils.py
gmsdk/views.py
gmsdk/wsgi.py
gmsdk.egg-info/PKG-INFO
gmsdk.egg-info/SOURCES.txt
gmsdk.egg-info/dependency_links.txt
gmsdk.egg-info/requires.txt
gmsdk.egg-info/top_level.txt