Metadata-Version: 1.1
Name: gmsdk
Version: 0.2.2
Summary: Python SDK for communicating Delhivery's - Warehouse Management System APIs for Order / Product / Supplier
Home-page: https://github.com/harikishan/godam-sdk
Author: Hari Kishan
Author-email: hari.kishan@delhivery.com
License: UNKNOWN
Platform: UNKNOWN
Classifier: Programming Language :: Python
Classifier: Programming Language :: Python :: 2
Classifier: License :: OSI Approved :: GNU General Public License (GPL)
Classifier: Operating System :: OS Independent
Classifier: Development Status :: 1 - Planning
Classifier: Environment :: Console
Classifier: Intended Audience :: Science/Research
Classifier: Topic :: Scientific/Engineering :: GIS
